pytest_sample/__init__.py
pytest_sample/_routing.py
pytest_sample/_version.py
pytest_sample/a.py
pytest_sample/resources/a.txt
pytest_sample/utils/__init__.py
anglisano-2.0.0.dist-info/LICENSE
anglisano-2.0.0.dist-info/METADATA
anglisano-2.0.0.dist-info/WHEEL
anglisano-2.0.0.dist-info/top_level.txt
anglisano-2.0.0.dist-info/zip-safe
anglisano-2.0.0.dist-info/RECORD
